needle/__init__.py
needle/bus/__init__.py
needle/bus/bridge.py
needle/bus/event.py
needle/bus/feedback.py
pyneedle_bus-0.1.4.dist-info/METADATA
pyneedle_bus-0.1.4.dist-info/WHEEL
pyneedle_bus-0.1.4.dist-info/RECORD
