Metadata-Version: 2.4
Name: pyneedle-bus
Version: 0.1.4
Summary: Unified EventBus (logic) and FeedbackBus (presentation) for the PyNeedle ecosystem.
Project-URL: Homepage, https://github.com/quipu-dev/Needle
Project-URL: Repository, https://github.com/quipu-dev/Needle
Project-URL: Bug Tracker, https://github.com/quipu-dev/Needle/issues
Author-email: doucx <doucxldh@gmail.com>
License: Apache-2.0
Keywords: bus,event,feedback,i18n,needle,pointer,semantic
Classifier: Development Status :: 3 - Alpha
Classifier: Intended Audience :: Developers
Classifier: License :: OSI Approved :: Apache Software License
Classifier: Operating System :: OS Independent
Classifier: Programming Language :: Python :: 3
Classifier: Programming Language :: Python :: 3.10
Classifier: Programming Language :: Python :: 3.11
Classifier: Programming Language :: Python :: 3.12
Classifier: Topic :: Software Development :: Libraries :: Python Modules
Classifier: Typing :: Typed
Requires-Python: >=3.10
Requires-Dist: pyneedle-pointer~=0.2.0
Requires-Dist: pyneedle-runtime~=0.1.4
Requires-Dist: pyneedle-spec~=0.1.4
